<?xml version="1.0" encoding="utf-8"?>
<odoo>

    <!-- Helpdesk Ticket with Resolution-->
    <record id="helpdesk_ticket_form_resolution" model="ir.ui.view">
        <field name="name">helpdesk.ticket.form.resolution</field>
        <field name="model">helpdesk.ticket</field>
        <field name="inherit_id" ref="helpdesk.helpdesk_ticket_view_form"/>
        <field name="arch" type="xml">
            <field name="description" position="after">
                <separator string="Resolution"/>
                <field name="resolution"/>
            </field>
        </field>
    </record>
</odoo>
